buttersalt_saltapi/__init__.py
buttersalt_saltapi/saltapi.py
buttersalt_saltapi-1.0.7.dist-info/METADATA
buttersalt_saltapi-1.0.7.dist-info/RECORD
buttersalt_saltapi-1.0.7.dist-info/WHEEL
buttersalt_saltapi-1.0.7.dist-info/top_level.txt
