Metadata-Version: 2.1
Name: buttersalt-saltapi
Version: 1.0.7
Summary: The ButterSalt wrapper around the salt-api
Home-page: https://github.com/lfzyx/ButterSalt-saltapi
Author: lfzyx
Author-email: lfzyx.me@gmail.com
License: MIT
Keywords: buttersalt saltapi
Platform: UNKNOWN
Classifier: Development Status :: 5 - Production/Stable
Classifier: Programming Language :: Python :: 3 :: Only
Classifier: License :: OSI Approved :: MIT License
Classifier: Topic :: Software Development :: Libraries :: Python Modules
Requires-Python: ~=3.6
Requires-Dist: requests
